python_som/__init__.py
python_som-0.1.3.dist-info/METADATA
python_som-0.1.3.dist-info/WHEEL
python_som-0.1.3.dist-info/licenses/LICENSE
python_som-0.1.3.dist-info/RECORD
