Metadata-Version: 2.4
Name: python-som
Version: 0.1.3
Summary: Python implementation of the Self-Organizing Map
Project-URL: Homepage, https://github.com/andremsouza/python-som
Project-URL: Issues, https://github.com/andremsouza/python-som/issues
Author-email: André Moreira Souza <msouza.andre@hotmail.com>
License-Expression: MIT
License-File: LICENSE
Classifier: Development Status :: 3 - Alpha
Classifier: Intended Audience :: Developers
Classifier: Intended Audience :: Science/Research
Classifier: License :: OSI Approved :: MIT License
Classifier: Operating System :: OS Independent
Classifier: Programming Language :: Python :: 3
Classifier: Topic :: Scientific/Engineering :: Artificial Intelligence
Classifier: Topic :: Software Development :: Libraries
Classifier: Topic :: Software Development :: Libraries :: Python Modules
Requires-Python: >=3.9
Requires-Dist: numpy
Requires-Dist: pandas
Requires-Dist: scikit-learn
Provides-Extra: cli
Requires-Dist: tqdm; extra == 'cli'
